sandhi/__init__.py
sandhi/apavaada.py
sandhi/cli.py
sandhi/niyama.py
sandhi/sandhi.py
sandhi-0.1.2.dist-info/AUTHORS.rst
sandhi-0.1.2.dist-info/LICENSE
sandhi-0.1.2.dist-info/METADATA
sandhi-0.1.2.dist-info/WHEEL
sandhi-0.1.2.dist-info/entry_points.txt
sandhi-0.1.2.dist-info/top_level.txt
sandhi-0.1.2.dist-info/RECORD
