Metadata-Version: 2.1
Name: sandhi
Version: 0.1.2
Summary: Sanskrit Sandhi Module
Home-page: https://github.com/hrishikeshrt/sandhi
Author: Hrishikesh Terdalkar
Author-email: hrishikeshrt@linuxmail.org
License: GNU General Public License v3
Keywords: sandhi
Classifier: Development Status :: 2 - Pre-Alpha
Classifier: Intended Audience :: Developers
Classifier: License :: OSI Approved :: GNU General Public License v3 (GPLv3)
Classifier: Natural Language :: English
Classifier: Programming Language :: Python :: 3
Classifier: Programming Language :: Python :: 3.6
Classifier: Programming Language :: Python :: 3.7
Classifier: Programming Language :: Python :: 3.8
Classifier: Programming Language :: Python :: 3.9
Classifier: Programming Language :: Python :: 3.10
Requires-Python: >=3.6
License-File: LICENSE
License-File: AUTHORS.rst
Requires-Dist: indic-transliteration
